cbc_api/ __init__.py
cbc_api/cbc_api.py
coinbase_commerce_API-1.0.3.dist-info/METADATA
coinbase_commerce_API-1.0.3.dist-info/WHEEL
coinbase_commerce_API-1.0.3.dist-info/top_level.txt
coinbase_commerce_API-1.0.3.dist-info/RECORD
